stransi/__init__.py
stransi/_misc.py
stransi/ansi.py
stransi/attribute.py
stransi/clear.py
stransi/color.py
stransi/cursor.py
stransi/escape.py
stransi/instruction.py
stransi/token.py
stransi/unsupported.py
stransi-0.3.0.dist-info/LICENSE
stransi-0.3.0.dist-info/WHEEL
stransi-0.3.0.dist-info/METADATA
stransi-0.3.0.dist-info/RECORD
