Metadata-Version: 2.1
Name: stransi
Version: 0.3.0
Summary: A lightweight parser for ANSI escape sequences
Home-page: https://github.com/getcuia/stransi
License: MIT
Keywords: ansi-colors,ansi-escape-codes,ansi,console,cuia,parser,stransi,terminal
Author: Felipe S. S. Schneider
Author-email: schneider.felipe@posgrad.ufsc.br
Requires-Python: >=3.8,<4.0
Classifier: Development Status :: 4 - Beta
Classifier: Intended Audience :: Developers
Classifier: License :: OSI Approved :: MIT License
Classifier: Programming Language :: Python :: 3
Classifier: Programming Language :: Python :: 3.10
Classifier: Programming Language :: Python :: 3.8
Classifier: Programming Language :: Python :: 3.9
Classifier: Topic :: Software Development :: Libraries :: Python Modules
Classifier: Topic :: Software Development :: User Interfaces
Classifier: Topic :: Terminals :: Terminal Emulators/X Terminals
Classifier: Topic :: Text Processing :: Markup
Requires-Dist: ochre (>=0.4.0,<0.5.0)
Project-URL: Repository, https://github.com/getcuia/stransi
